{"195295": ["future", "epistemic non-assertive", "long or short yiqtol"], "195349": ["future", "epistemic non-assertive", "long or short yiqtol"], "195404": ["future", "epistemic non-assertive", "long or short yiqtol"], "195462": ["deontic other", "epistemic non-assertive", "long yiqtol"], "195466": ["future", "long or short yiqtol"], "195473": ["deontic other", "short yiqtol"], "195486": ["future", "epistemic non-assertive", "long yiqtol"], "195491": ["future indicated by context and supported by parallel \u05d9\u05d4\u05d9\u05d4; short form perhaps triggered by sentence structure?", "future", "short yiqtol"], "195498": ["future", "long yiqtol"], "195639": ["deontic permissive", "long or short yiqtol"], "195642": ["indirect volitional final", "deontic permissive", "long or short yiqtol"], "195663": ["deontic prohibitive", "long or short yiqtol"], "195699": ["deontic prohibitive", "long or short yiqtol"], "195760": ["future", "long yiqtol"], "195278": ["deontic obligative"], "195328": ["deontic obligative"], "195334": ["deontic obligative"], "195383": ["deontic obligative"], "195388": ["deontic obligative"], "195460": ["deontic permissive"], "195671": ["deontic permissive"], "195727": ["deontic obligative"], "195732": ["deontic obligative"], "195805": ["deontic other", "deontic obligative"], "195807": ["deontic other", "deontic obligative"]}